<?xml version="1.0" encoding="UTF-8"?><scenario>
    <world>
        <region name="India">
            <ghgpolicy name="CO2Cement">
                <market>India</market>
                <constraint year="2025">56.2</constraint>
                <constraint year="2030">60.18</constraint>
               <constraint year="2035">60.92</constraint>
              <constraint year="2040">58.1</constraint>
                <constraint year="2045">41.83</constraint>
                <constraint year="2050">30.44</constraint>
              <constraint year="2055">19.48</constraint>
                <constraint year="2060">9.65</constraint>
                <constraint year="2065">2.78</constraint>
                <constraint year="2070">0.01</constraint>
              <!--   <constraint year="2075">80</constraint>
                <constraint year="2080">80</constraint>
                <constraint year="2085">80</constraint>
                <constraint year="2090">80</constraint>
                <constraint year="2095">80</constraint>
                <constraint year="2100">80</constraint>  -->
            </ghgpolicy>
        </region>
    </world>
</scenario>