<?xml version="1.0" encoding="UTF-8"?><scenario>
    <world>
        <region name="India">
            <ghgpolicy name="CO2IRSTL">
                <market>India</market>
                <constraint year="2025">106.54070897372337</constraint>
                <constraint year="2030">114.09005453644026</constraint>
             <constraint year="2035">117.77814576103123</constraint>
               <constraint year="2040">115.36864154685175</constraint>
                <constraint year="2045">64.7281110560238</constraint>
                <constraint year="2050">33.255453644025785</constraint>
              <!--   <constraint year="2055">100</constraint>
                <constraint year="2060">100</constraint>
                <constraint year="2065">100</constraint>
                <constraint year="2070">80</constraint>
                <constraint year="2075">80</constraint>
                <constraint year="2080">80</constraint>
                <constraint year="2085">80</constraint>
                <constraint year="2090">80</constraint>
                <constraint year="2095">80</constraint>
                <constraint year="2100">80</constraint> -->
            </ghgpolicy>
        </region>
    </world>
</scenario>
